{
  "Metadata": {
    "Driver": "COL5A2",
    "Version": "1.0",
    "Pipeline": "CCNIF",
    "Created": "2026-07-09 13:59:04.629009"
  },
  "Evidence": {
    "File": "results/evidence/COL5A2/Evidence/Transcriptomics_Evidence.json",
    "Exists": true,
    "Size": 616,
    "Modified": "2026-07-09 13:59:04.106524"
  },
  "Statistics": {
    "File": "results/evidence/COL5A2/Statistics/Models/Transcriptomics_Model.json",
    "Exists": false,
    "Size": null,
    "Modified": null
  },
  "Diagnostics": {
    "File": "results/evidence/COL5A2/Statistics/Diagnostics/Transcriptomics_Diagnostics.json",
    "Exists": false,
    "Size": null,
    "Modified": null
  },
  "Normalization": {
    "File": "results/evidence/COL5A2/Statistics/Normalization_Report.json",
    "Exists": true,
    "Size": 404,
    "Modified": "2026-07-09 13:59:04.618169"
  },
  "Quality": {
    "File": "results/evidence/COL5A2/Statistics/Quality_Report.json",
    "Exists": true,
    "Size": 279,
    "Modified": "2026-07-09 13:59:04.622135"
  },
  "Confidence": {
    "File": "results/evidence/COL5A2/Statistics/Confidence_Report.json",
    "Exists": true,
    "Size": 293,
    "Modified": "2026-07-09 13:59:04.622135"
  },
  "DriverReport": {
    "File": "results/evidence/COL5A2/Driver_Report.json",
    "Exists": true,
    "Size": 2036,
    "Modified": "2026-07-09 13:59:04.626101"
  }
}
