{
  "Metadata": {
    "Driver": "MUC16",
    "Version": "1.0",
    "Pipeline": "CCNIF",
    "Created": "2026-07-09 16:27:00.84294"
  },
  "Evidence": {
    "File": "results/evidence/MUC16/Evidence/Transcriptomics_Evidence.json",
    "Exists": true,
    "Size": 609,
    "Modified": "2026-07-09 16:24:46.366721"
  },
  "Statistics": {
    "File": "results/evidence/MUC16/Statistics/Models/Transcriptomics_Model.json",
    "Exists": false,
    "Size": null,
    "Modified": null
  },
  "Diagnostics": {
    "File": "results/evidence/MUC16/Statistics/Diagnostics/Transcriptomics_Diagnostics.json",
    "Exists": false,
    "Size": null,
    "Modified": null
  },
  "Normalization": {
    "File": "results/evidence/MUC16/Statistics/Normalization_Report.json",
    "Exists": true,
    "Size": 408,
    "Modified": "2026-07-09 16:27:00.831167"
  },
  "Quality": {
    "File": "results/evidence/MUC16/Statistics/Quality_Report.json",
    "Exists": true,
    "Size": 279,
    "Modified": "2026-07-09 16:27:00.835326"
  },
  "Confidence": {
    "File": "results/evidence/MUC16/Statistics/Confidence_Report.json",
    "Exists": true,
    "Size": 291,
    "Modified": "2026-07-09 16:27:00.835326"
  },
  "DriverReport": {
    "File": "results/evidence/MUC16/Driver_Report.json",
    "Exists": true,
    "Size": 2030,
    "Modified": "2026-07-09 16:27:00.839486"
  }
}
